nipanbo_mcp_educate_time/__init__.py
nipanbo_mcp_educate_time/server.py
nipanbo_mcp_educate_time-0.1.0.dist-info/METADATA
nipanbo_mcp_educate_time-0.1.0.dist-info/WHEEL
nipanbo_mcp_educate_time-0.1.0.dist-info/top_level.txt
nipanbo_mcp_educate_time-0.1.0.dist-info/RECORD
