Metadata-Version: 2.4
Name: nipanbo-mcp-educate-time
Version: 0.1.0
Summary: Add your description here
Home-page: https://github.com/luoyingguo?tab=repositories
Author: rong
Author-email: 417028634@qq.com
Requires-Python: >=3.12
Requires-Dist: mcp[cli]>=1.7.1
Requires-Dist: setuptools>=80.3.1
Requires-Dist: twine>=6.1.0
Requires-Dist: wheel>=0.45.1
Dynamic: author
Dynamic: author-email
Dynamic: home-page
Dynamic: requires-python
